opencv_calibrate/__init__.py
opencv_calibrate/calibrate.py
opencv_calibrate/camera.py
opencv_calibrate/debug.py
opencv_calibrate/io.py
opencv_calibrate/utils.py
opencv_calibrate-0.1.1.dist-info/LICENSE
opencv_calibrate-0.1.1.dist-info/METADATA
opencv_calibrate-0.1.1.dist-info/WHEEL
opencv_calibrate-0.1.1.dist-info/entry_points.txt
opencv_calibrate-0.1.1.dist-info/top_level.txt
opencv_calibrate-0.1.1.dist-info/RECORD
