Metadata-Version: 2.1
Name: opencv_calibrate
Version: 0.1.1
Summary: A simple OpenCV checkerboard camera calibration python package
Author: Alfie
Project-URL: Homepage, https://github.com/alfieroddan/camera-calibration-opencv
Project-URL: Bug Tracker, https://github.com/alfieroddan/camera-calibration-opencv/issues
Classifier: Programming Language :: Python :: 3
Classifier: License :: OSI Approved :: MIT License
Classifier: Operating System :: OS Independent
Requires-Python: >=3.7
License-File: LICENSE
Requires-Dist: opencv-python
Requires-Dist: numpy
Requires-Dist: tqdm
Requires-Dist: argparse
Requires-Dist: ffmpeg-python
Requires-Dist: pillow
Requires-Dist: pillow-heif
Requires-Dist: pyyaml
